[{"model": "CaptainConsole.category", "pk": 1, "fields": {"name": "Nintendo", "parent": null, "slug": "nintendo", "lft": 1, "rght": 4, "tree_id": 1, "level": 0}}, {"model": "CaptainConsole.category", "pk": 2, "fields": {"name": "Super Nintendo", "parent": 1, "slug": "super-nintendo", "lft": 2, "rght": 3, "tree_id": 1, "level": 1}}, {"model": "CaptainConsole.category", "pk": 3, "fields": {"name": "Sega", "parent": null, "slug": "sega", "lft": 1, "rght": 6, "tree_id": 2, "level": 0}}, {"model": "CaptainConsole.category", "pk": 4, "fields": {"name": "Genesis/Megadrive", "parent": 3, "slug": "genesis", "lft": 2, "rght": 5, "tree_id": 2, "level": 1}}, {"model": "CaptainConsole.category", "pk": 5, "fields": {"name": "Sony", "parent": null, "slug": "sony", "lft": 1, "rght": 6, "tree_id": 3, "level": 0}}, {"model": "CaptainConsole.category", "pk": 6, "fields": {"name": "PlayStation", "parent": 5, "slug": "playstation", "lft": 2, "rght": 3, "tree_id": 3, "level": 1}}, {"model": "CaptainConsole.category", "pk": 7, "fields": {"name": "PlayStation 2", "parent": 5, "slug": "playstation-2", "lft": 4, "rght": 5, "tree_id": 3, "level": 1}}, {"model": "CaptainConsole.category", "pk": 8, "fields": {"name": "Sega CD", "parent": 4, "slug": "sega-cd", "lft": 3, "rght": 4, "tree_id": 2, "level": 2}}